bfgdealer/__init__.py
bfgdealer/_version.py
bfgdealer/board.py
bfgdealer/constants.py
bfgdealer/dealer.py
bfgdealer/dealer_duo.py
bfgdealer/dealer_engine.py
bfgdealer/dealer_solo.py
bfgdealer-0.0.22.dist-info/WHEEL
bfgdealer-0.0.22.dist-info/METADATA
bfgdealer-0.0.22.dist-info/RECORD
