Metadata-Version: 2.3
Name: bfgdealer
Version: 0.0.22
Summary: Dealer for BfG
Author: Jeff
Author-email: Jeff <jeffwatkins2000@gmail.com>
Requires-Dist: bfgbidding
Requires-Dist: bridgeobjects>=0.1.30
Requires-Dist: endplay>=0.5.12
Requires-Dist: termcolor>=3.1.0
Requires-Python: >=3.10
